AUTHORS
CHANGELOG
LICENSE
MANIFEST.in
README.rst
setup.py
transmanager/__init__.py
transmanager/admin.py
transmanager/apps.py
transmanager/export.py
transmanager/forms.py
transmanager/manager.py
transmanager/mixins.py
transmanager/models.py
transmanager/permissions.py
transmanager/search_indexes.py
transmanager/serializers.py
transmanager/settings.py
transmanager/signals.py
transmanager/tables.py
transmanager/urls.py
transmanager/utils.py
transmanager/views.py
transmanager.egg-info/PKG-INFO
transmanager.egg-info/SOURCES.txt
transmanager.egg-info/dependency_links.txt
transmanager.egg-info/requires.txt
transmanager.egg-info/top_level.txt
transmanager/__pycache__/__init__.cpython-34.pyc
transmanager/__pycache__/__init__.cpython-35.pyc
transmanager/__pycache__/admin.cpython-34.pyc
transmanager/__pycache__/admin.cpython-35.pyc
transmanager/__pycache__/apps.cpython-34.pyc
transmanager/__pycache__/apps.cpython-35.pyc
transmanager/__pycache__/export.cpython-34.pyc
transmanager/__pycache__/export.cpython-35.pyc
transmanager/__pycache__/forms.cpython-34.pyc
transmanager/__pycache__/forms.cpython-35.pyc
transmanager/__pycache__/manager.cpython-34.pyc
transmanager/__pycache__/manager.cpython-35.pyc
transmanager/__pycache__/mixins.cpython-34.pyc
transmanager/__pycache__/mixins.cpython-35.pyc
transmanager/__pycache__/models.cpython-34.pyc
transmanager/__pycache__/models.cpython-35.pyc
transmanager/__pycache__/permissions.cpython-34.pyc
transmanager/__pycache__/permissions.cpython-35.pyc
transmanager/__pycache__/search_indexes.cpython-34.pyc
transmanager/__pycache__/search_indexes.cpython-35.pyc
transmanager/__pycache__/serializers.cpython-34.pyc
transmanager/__pycache__/serializers.cpython-35.pyc
transmanager/__pycache__/settings.cpython-34.pyc
transmanager/__pycache__/settings.cpython-35.pyc
transmanager/__pycache__/signals.cpython-34.pyc
transmanager/__pycache__/signals.cpython-35.pyc
transmanager/__pycache__/tables.cpython-34.pyc
transmanager/__pycache__/tables.cpython-35.pyc
transmanager/__pycache__/urls.cpython-34.pyc
transmanager/__pycache__/urls.cpython-35.pyc
transmanager/__pycache__/utils.cpython-34.pyc
